Workbook

Sheet Planilha1
B9: CONFIGURAÇÕES
B10: Salário | D10: 5000
B11: Rendimento Carteria | D11: 0.006
B12: Sugestão investimento | D12: =D10*30% -> 1500
B14: INVESTIMENTO MENSAL
B15: Quanto investir mês | D15: 500
B16: Quantos anos | D16: 5
B17: Taxa de rendimento mensal | D17: 0.0108
B18: Patrimônio Acumulado | D18: =FV(D17,D16*12,D15*-1) -> 41902.01
B19: Dividendos Mensais | D19: =D18*D17 -> 452.5417
B21: Cenários | D21: Dividendo
A22: 2 | B22: Quanto em 2 anos | C22: =FV($D$17,$A22*12,$D$15*-1) -> 13615.432 | D22: =C22*$D$11 -> 81.692591
A23: 5 | B23: Quanto em 5 anos | C23: =FV($D$17,$A23*12,$D$15*-1) -> 41902.01 | D23: =C23*$D$11 -> 251.41206
A24: 10 | B24: Quanto em 10 anos | C24: =FV($D$17,$A24*12,$D$15*-1) -> 121728.83 | D24: =C24*$D$11 -> 730.373
A25: 20 | B25: Quanto em 20 anos | C25: =FV($D$17,$A25*12,$D$15*-1) -> 563524.5 | D25: =C25*$D$11 -> 3381.147
A26: 30 | B26: Quanto em 30 anos | C26: =FV($D$17,$A26*12,$D$15*-1) -> 2166952.4 | D26: =C26*$D$11 -> 13001.714
B30: Perfil | C30: CONSERVADOR
B31: Valor a ser investido mês | C31: =D15 -> 500
B33: TIPOS DE FIIS | C33: Percentual Sugerido | D33: Valores
B34: PAPEL | C34: =VLOOKUP($C$30&"-"&B34,Planilha2!$A:$D,4,FALSE()) -> 0.3 | D34: =C34*$C$31 -> 150
B35: TIJOLO | C35: =VLOOKUP($C$30&"-"&B35,Planilha2!$A:$D,4,FALSE()) -> 0.5 | D35: =C35*$C$31 -> 250
B36: HÍBRIDOS | C36: =VLOOKUP($C$30&"-"&B36,Planilha2!$A:$D,4,FALSE()) -> 0.1 | D36: =C36*$C$31 -> 50
B37: FOF´S | C37: =VLOOKUP($C$30&"-"&B37,Planilha2!$A:$D,4,FALSE()) -> 0.1 | D37: =C37*$C$31 -> 50
B38: DESENVOLVIMENTO | C38: =VLOOKUP($C$30&"-"&B38,Planilha2!$A:$D,4,FALSE()) -> 0 | D38: =C38*$C$31 -> 0
B39: HOTELARIAS | C39: =VLOOKUP($C$30&"-"&B39,Planilha2!$A:$D,4,FALSE()) -> 0 | D39: =C39*$C$31 -> 0
D40: =SUM(D34:D39) -> 500

Sheet Planilha2
A1: CHAVE | B1: PERFIL | C1: TIPO DE FII | D1: %
A2: =B2&"-"&C2 -> CONSERVADOR-PAPEL | B2: CONSERVADOR | C2: PAPEL | D2: 0.3
A3: =B3&"-"&C3 -> CONSERVADOR-TIJOLO | B3: CONSERVADOR | C3: TIJOLO | D3: 0.5
A4: =B4&"-"&C4 -> CONSERVADOR-HÍBRIDOS | B4: CONSERVADOR | C4: HÍBRIDOS | D4: 0.1
A5: =B5&"-"&C5 -> CONSERVADOR-FOF´S | B5: CONSERVADOR | C5: FOF´S | D5: 0.1
A6: =B6&"-"&C6 -> CONSERVADOR-DESENVOLVIMENTO | B6: CONSERVADOR | C6: DESENVOLVIMENTO | D6: 0
A7: =B7&"-"&C7 -> CONSERVADOR-HOTELARIAS | B7: CONSERVADOR | C7: HOTELARIAS | D7: 0
A8: =B8&"-"&C8 -> MODERADO-PAPEL | B8: MODERADO | C8: PAPEL | D8: 0.32
A9: =B9&"-"&C9 -> MODERADO-TIJOLO | B9: MODERADO | C9: TIJOLO | D9: 0.35
A10: =B10&"-"&C10 -> MODERADO-HÍBRIDOS | B10: MODERADO | C10: HÍBRIDOS | D10: 0.08
A11: =B11&"-"&C11 -> MODERADO-FOF´S | B11: MODERADO | C11: FOF´S | D11: 0.05
A12: =B12&"-"&C12 -> MODERADO-DESENVOLVIMENTO | B12: MODERADO | C12: DESENVOLVIMENTO | D12: 0.1
A13: =B13&"-"&C13 -> MODERADO-HOTELARIAS | B13: MODERADO | C13: HOTELARIAS | D13: 0.1
... A19: =B19&"-"&C19 -> AGRESSIVO-HOTELARIAS | B19: AGRESSIVO | C19: HOTELARIAS | D19: 0.1
